CHANGELOG.txt
ChromeDriverDownloader.py
LICENCE.txt
MANIFEST.in
README.txt
__init__.py
main.py
setup.py
chromedriverdownloaderandchecker.egg-info/PKG-INFO
chromedriverdownloaderandchecker.egg-info/SOURCES.txt
chromedriverdownloaderandchecker.egg-info/dependency_links.txt
chromedriverdownloaderandchecker.egg-info/top_level.txt